[
    {
        "id": 1,
        "songNo": 1,
        "title": "Aathmamae Un Aandavarin",
        "tamilTitle": "ஆத்மமே உன் ஆண்டவரின்",
        "artist": null,
        "type": "PAMALAI",
        "category": {
            "name": "workship song"
        },
        "pallavi": null,
        "anuPallavi": null,
        "stanzas": ["ஆத்மமே, உன் ஆண்டவரின்\r\nதிருப்பாதம் பணிந்து,\r\nமீட்பு, சுகம், ஜீவன், அருள்\r\nபெற்றதாலே துதித்து,\r\nஅல்லேலுயா, என்றென்றைக்கும்\r\nநித்திய நாதரைப்போற்று.", "நம் பிதாக்கள் தாழ்வில் பெற்ற\r\nதயை நன்மைக்காய் துதி;\r\nகோபங்கொண்டும் அருள் ஈயும்\r\nஎன்றும் மாறாதோர் துதி;\r\nஅல்லேலுயா, அவர் உண்மை\r\nமா மகிமையாம் துதி.", "தயை உள்ளோர்;\r\nநீச மண்ணோர் நம்மையே\r\nஅன்பின் கரம் கொண்டு தாங்கி\r\nமாற்றார் வீழ்த்திக் காப்பாரே!\r\nஅல்லேலுயா, இன்னும் அவர்\r\nஅருள் விரிவானதே.", "என்றும் நின்றவர் சமுகம்\r\nபோற்றும் தூதர் கூட்டமே,\r\nநாற்றிசையும் நின்றெழுத்து\r\nபணிவர் நீர் பக்தரே;\r\nஅல்லேலுயா, அனைவோரும்\r\nஅன்பின் தெய்வம் போற்றுமே."]
    }
]